schemas/__init__.py
schemas/ajson.py
schemas/aresti.py
schemas/fcj.py
schemas/ma.py
schemas/maninfo.py
schemas/positioning.py
schemas/py.typed
schemas/sdef.py
schemas/sinfo.py
schemas/utils/__init__.py
schemas/utils/enum.py
schemas/utils/files.py
pfcschemas-0.1.13.dist-info/METADATA
pfcschemas-0.1.13.dist-info/WHEEL
pfcschemas-0.1.13.dist-info/RECORD
